shipyard_dropbox/__init__.py
shipyard_dropbox/cli/__init__.py
shipyard_dropbox/cli/authtest.py
shipyard_dropbox/cli/download.py
shipyard_dropbox/cli/upload.py
shipyard_dropbox/dropbox.py
shipyard_dropbox-0.1.1.dist-info/METADATA
shipyard_dropbox-0.1.1.dist-info/WHEEL
shipyard_dropbox-0.1.1.dist-info/RECORD
