Metadata-Version: 2.1
Name: shipyard-dropbox
Version: 0.1.1
Summary: A local client to connect and work with Dropox
License: Apache 2.0
Author: wrp801
Author-email: wespoulsen@gmail.com
Requires-Python: >=3.9,<4.0
Classifier: License :: Other/Proprietary License
Classifier: Programming Language :: Python :: 3
Classifier: Programming Language :: Python :: 3.9
Classifier: Programming Language :: Python :: 3.10
Classifier: Programming Language :: Python :: 3.11
Requires-Dist: dropbox (>=11.36.2,<12.0.0)
Requires-Dist: shipyard-bp-utils (>=1.2.0,<2.0.0)
Requires-Dist: shipyard-templates (>=0.7.0,<0.8.0)
